django_etf_api/__init__.py
django_etf_api/admin.py
django_etf_api/apps.py
django_etf_api/models.py
django_etf_api/views.py
django_etf_api/management/__init__.py
django_etf_api/management/commands/__init__.py
django_etf_api/management/commands/calculate_indicators.py
django_etf_api/management/commands/fetch_etfs_data.py
django_etf_api/management/commands/generate_signals.py
django_etf_api/management/commands/print_etf_data.py
django_etf_api/management/commands/utils/base_command.py
django_etf_api/management/commands/utils/etf_config.py
django_etf_api/management/commands/utils/tools.py
django_etf_api/migrations/0001_initial.py
django_etf_api/migrations/0002_etfdetails_last_price_date.py
django_etf_api/migrations/__init__.py
django_etf_api/tests/__init__.py
django_etf_api/tests/test_calculate_indicators.py
django_etf_api/tests/test_fetch_etfs_data.py
django_etf_api/tests/test_generate_signals.py
django_etf_api/tests/test_models.py
django_etf_api/tests/test_print_etf_data.py
django_etf_api-0.1.0.dist-info/licenses/LICENSE
django_etf_api-0.1.0.dist-info/METADATA
django_etf_api-0.1.0.dist-info/WHEEL
django_etf_api-0.1.0.dist-info/top_level.txt
django_etf_api-0.1.0.dist-info/RECORD
